setupCLI/__init__.py
setupCLI/__main__.py
setupCLI-0.0.1.dist-info/METADATA
setupCLI-0.0.1.dist-info/WHEEL
setupCLI-0.0.1.dist-info/dependency_links.txt
setupCLI-0.0.1.dist-info/entry_points.txt
setupCLI-0.0.1.dist-info/top_level.txt
setupCLI-0.0.1.dist-info/RECORD
